forestplot/__init__.py
forestplot/arg_validators.py
forestplot/dataframe_utils.py
forestplot/graph_utils.py
forestplot/mplot.py
forestplot/mplot_dataframe_utils.py
forestplot/mplot_graph_utils.py
forestplot/plot.py
forestplot/text_utils.py
forestplot-0.4.0.dist-info/LICENSE
forestplot-0.4.0.dist-info/METADATA
forestplot-0.4.0.dist-info/WHEEL
forestplot-0.4.0.dist-info/top_level.txt
forestplot-0.4.0.dist-info/RECORD
