Metadata-Version: 2.1
Name: forestplot
Version: 0.4.0
Summary: A Python package to make publication-ready but customizable forest plots.
Home-page: https://github.com/lsys/forestplot
Author: Lucas Shen
Author-email: lucas@lucasshen.com
Maintainer: Lucas Shen
Maintainer-email: lucas@lucasshen.com
License: MIT
Keywords: visualization,python,data-science,dataviz,pandas,matplotlib,mpl,forestplot,blobbogram
Platform: UNKNOWN
Classifier: License :: OSI Approved :: MIT License
Classifier: Natural Language :: English
Classifier: Programming Language :: Python :: 3
Classifier: Programming Language :: Python :: 3.6
Classifier: Programming Language :: Python :: 3.7
Classifier: Programming Language :: Python :: 3.8
Classifier: Programming Language :: Python :: 3.9
Classifier: Programming Language :: Python :: 3.10
License-File: LICENSE
Requires-Dist: pandas
Requires-Dist: numpy
Requires-Dist: matplotlib
Requires-Dist: matplotlib-inline (<=0.1.3)
